{
  "sections": {
    "main": {
      "type": "template-page",
      "disabled": true,
      "settings": {
      }
    },
    "klaviyo_form_w68Agp": {
      "type": "klaviyo-form",
      "settings": {
        "desktop-image": "shopify:\/\/shop_images\/D2C_SMS_Sign_Up_Landing_Page_4.png",
        "desktop_form_position": "left",
        "mobile-image": "shopify:\/\/shop_images\/D2C_Email_SMS_Sign_Up_Landing_Page_15.png",
        "form-code": "<div class=\"klaviyo-form-X2qgnC\"><\/div>"
      }
    }
  },
  "order": [
    "main",
    "klaviyo_form_w68Agp"
  ]
}